kedixa/__init__.py
kedixa/compat.py
kedixa/file_loader.py
kedixa/mprocess.py
kedixa/qps_pool.py
kedixa/version.py
kedixa/comm/__init__.py
kedixa/comm/address.py
kedixa/comm/basic.py
kedixa/comm/bridge.py
kedixa/comm/connection.py
kedixa/comm/debug_transformer.py
kedixa/comm/exception.py
kedixa/comm/file_adaptor.py
kedixa/comm/read_until_transformer.py
kedixa/comm/socket_adaptor.py
kedixa/comm/speed_limit_transformer.py
kedixa/comm/ssl_transformer.py
kedixa/comm/tcp_server.py
kedixa/comm/http/__init__.py
kedixa/comm/http/http_chunk_transformer.py
kedixa/comm/http/http_code_map.py
kedixa/comm/http/http_message.py
kedixa/comm/http/http_proxy_upgrader.py
kedixa/comm/websocket/__init__.py
kedixa/comm/websocket/websocket_handler.py
kedixa/comm/websocket/websocket_message.py
kedixa/comm/websocket/websocket_processor.py
kedixa/comm/websocket/websocket_upgrader.py
kedixa-0.0.6.dist-info/METADATA
kedixa-0.0.6.dist-info/WHEEL
kedixa-0.0.6.dist-info/top_level.txt
kedixa-0.0.6.dist-info/RECORD
