Metadata-Version: 2.1
Name: kedixa
Version: 0.0.6
Summary: kedixa's personal python toy library
Home-page: https://github.com/kedixa/pykedixa/
Author: kedixa
License: UNKNOWN
Platform: UNKNOWN
Requires-Python: >=3.6
